aliyunsdkfoas/__init__.py
aliyunsdkfoas/endpoint.py
aliyunsdkfoas/request/__init__.py
aliyunsdkfoas/request/v20181111/BatchGetInstanceRunSummaryRequest.py
aliyunsdkfoas/request/v20181111/BindQueueRequest.py
aliyunsdkfoas/request/v20181111/CalcPlanJsonResourceRequest.py
aliyunsdkfoas/request/v20181111/CheckRawPlanJsonRequest.py
aliyunsdkfoas/request/v20181111/CommitJobRequest.py
aliyunsdkfoas/request/v20181111/CreateCellClusterOrderRequest.py
aliyunsdkfoas/request/v20181111/CreateClusterRequest.py
aliyunsdkfoas/request/v20181111/CreateFolderRequest.py
aliyunsdkfoas/request/v20181111/CreateJobRequest.py
aliyunsdkfoas/request/v20181111/CreatePackageRequest.py
aliyunsdkfoas/request/v20181111/CreateProjectRequest.py
aliyunsdkfoas/request/v20181111/CreateQueueRequest.py
aliyunsdkfoas/request/v20181111/DeleteFolderRequest.py
aliyunsdkfoas/request/v20181111/DeleteJobRequest.py
aliyunsdkfoas/request/v20181111/DeletePackageRequest.py
aliyunsdkfoas/request/v20181111/DeleteProjectRequest.py
aliyunsdkfoas/request/v20181111/DeleteQueueRequest.py
aliyunsdkfoas/request/v20181111/DestroyClusterRequest.py
aliyunsdkfoas/request/v20181111/ExpandClusterRequest.py
aliyunsdkfoas/request/v20181111/GetClusterDetailsRequest.py
aliyunsdkfoas/request/v20181111/GetClusterEngineVersionsRequest.py
aliyunsdkfoas/request/v20181111/GetClusterMetricsRequest.py
aliyunsdkfoas/request/v20181111/GetClusterQueueInfoRequest.py
aliyunsdkfoas/request/v20181111/GetClusterResourceRequest.py
aliyunsdkfoas/request/v20181111/GetFolderRequest.py
aliyunsdkfoas/request/v20181111/GetInstanceCheckpointRequest.py
aliyunsdkfoas/request/v20181111/GetInstanceConfigRequest.py
aliyunsdkfoas/request/v20181111/GetInstanceDetailRequest.py
aliyunsdkfoas/request/v20181111/GetInstanceExceptionsRequest.py
aliyunsdkfoas/request/v20181111/GetInstanceFinalStateRequest.py
aliyunsdkfoas/request/v20181111/GetInstanceHistoryAutoScalePlanContentRequest.py
aliyunsdkfoas/request/v20181111/GetInstanceHistoryAutoScalePlanListRequest.py
aliyun_python_sdk_foas-2.11.1.dist-info/LICENSE
aliyun_python_sdk_foas-2.11.1.dist-info/METADATA
aliyun_python_sdk_foas-2.11.1.dist-info/WHEEL
aliyun_python_sdk_foas-2.11.1.dist-info/top_level.txt
aliyun_python_sdk_foas-2.11.1.dist-info/RECORD
